LICENSE.txt
README.md
setup.py
pretty_data/EDA.py
pretty_data/__init__.py
pretty_data/general_info.py
pretty_data/manipulators.py
pretty_data.egg-info/PKG-INFO
pretty_data.egg-info/SOURCES.txt
pretty_data.egg-info/dependency_links.txt
pretty_data.egg-info/requires.txt
pretty_data.egg-info/top_level.txt